{"artists":[{"idArtist":"117662","strArtist":"Ras Kass","strArtistStripped":null,"strArtistAlternate":"","strLabel":null,"idLabel":null,"intFormedYear":"1994","intBornYear":"1972","intDiedYear":null,"strDisbanded":null,"strStyle":"Urban/R&B","strGenre":"Hip-Hop","strMood":"Confrontational","strWebsite":"","strFacebook":"","strTwitter":"1","strBiographyEN":"John Austin IV, (born September 26, 1973) better known by his stage name Ras Kass, is an American rapper. He is a member of the hip hop supergroup The HRSMN along with Canibus, Killah Priest, and Kurupt. He's also a member of the group Golden State Warriors with Xzibit and Saafir. Editors of About.com ranked him #30 on their list of the Top 50 MCs of Our Time (1987\u20132007).\nPitchfork Media called him \"one of the best rappers of all time.\"","strBiographyDE":null,"strBiographyFR":null,"strBiographyCN":null,"strBiographyIT":null,"strBiographyJP":null,"strBiographyRU":null,"strBiographyES":null,"strBiographyPT":null,"strBiographySE":null,"strBiographyNL":null,"strBiographyHU":null,"strBiographyNO":null,"strBiographyIL":null,"strBiographyPL":null,"strGender":"Male","intMembers":"1","strCountry":"Carson, CA, USA","strCountryCode":"US","strArtistThumb":"https://www.theaudiodb.com/images/media/artist/thumb/uywqxv1405766996.jpg","strArtistLogo":null,"strArtistCutout":null,"strArtistClearart":null,"strArtistWideThumb":null,"strArtistFanart":"https://www.theaudiodb.com/images/media/artist/fanart/uswsys1405767052.jpg","strArtistFanart2":null,"strArtistFanart3":null,"strArtistFanart4":null,"strArtistBanner":null,"strMusicBrainzID":"ccceb435-efd5-426a-bcdc-024262712525","strISNIcode":null,"strLastFMChart":null,"intCharted":"3","strLocked":"unlocked"}]}